README.md
setup.cfg
setup.py
MLNN/MLNN.py
MLNN/__init__.py
MLNN.egg-info/PKG-INFO
MLNN.egg-info/SOURCES.txt
MLNN.egg-info/dependency_links.txt
MLNN.egg-info/not-zip-safe
MLNN.egg-info/top_level.txt