Metadata-Version: 2.1
Name: MLNN
Version: 2.1
Summary: Multi-layer neuron network
Home-page: UNKNOWN
Author: vladgap
Author-email: gaponenko.vladimir@gmail.com
License: UNKNOWN
Platform: UNKNOWN
